LICENSE
MANIFEST.in
README.rst
setup.py
django_session_csrf_cookie.egg-info/PKG-INFO
django_session_csrf_cookie.egg-info/SOURCES.txt
django_session_csrf_cookie.egg-info/dependency_links.txt
django_session_csrf_cookie.egg-info/not-zip-safe
django_session_csrf_cookie.egg-info/requires.txt
django_session_csrf_cookie.egg-info/top_level.txt
session_csrf_cookie/__init__.py
session_csrf_cookie/models.py
session_csrf_cookie/tests.py