Metadata-Version: 1.0
Name: django-session-csrf-cookie
Version: 0.1
Summary: Django middleware that works with session-csrf and sends a CSRF token cookie.
Home-page: http://github.com/trustcentric/django-session-csrf-cookie
Author: Jody McIntyre
Author-email: jodym@trustcentric.com
License: BSD
Platform: UNKNOWN
Classifier: Development Status :: 4 - Beta
Classifier: Environment :: Web Environment
Classifier: Environment :: Web Environment :: Mozilla
Classifier: Framework :: Django
Classifier: Intended Audience :: Developers
Classifier: License :: OSI Approved :: BSD License
Classifier: Operating System :: OS Independent
Classifier: Programming Language :: Python
Classifier: Topic :: Software Development :: Libraries :: Python Modules
